kivymvp
