Metadata-Version: 1.0
Name: kivymvp
Version: 0.1.10
Summary: ui framework for kivy following the MVP pattern
Home-page: https://github.com/mkraemer67/kivymvp
Author: Martin Krämer
Author-email: mkraemer.de@gmail.com
License: Apache
Platform: UNKNOWN
